better_py/__init__.py
better_py/collections/__init__.py
better_py/collections/persistent_list.py
better_py/collections/persistent_map.py
better_py/collections/persistent_set.py
better_py/functions/__init__.py
better_py/functions/compose.py
better_py/functions/curry.py
better_py/functions/pipe.py
better_py/monads/__init__.py
better_py/monads/async_maybe.py
better_py/monads/async_result.py
better_py/monads/either.py
better_py/monads/io.py
better_py/monads/maybe.py
better_py/monads/reader.py
better_py/monads/result.py
better_py/monads/state.py
better_py/monads/task.py
better_py/monads/try_.py
better_py/monads/unit.py
better_py/monads/validation.py
better_py/monads/writer.py
better_py/protocols/__init__.py
better_py/protocols/combinable.py
better_py/protocols/mappable.py
better_py/protocols/parseable.py
better_py/protocols/reducible.py
better_py/protocols/traversable.py
better_py/protocols/types.py
better_py/protocols/updatable.py
better_py/protocols/validable.py
better_py_fp-0.2.0.dist-info/METADATA
better_py_fp-0.2.0.dist-info/WHEEL
better_py_fp-0.2.0.dist-info/licenses/AUTHORS.md
better_py_fp-0.2.0.dist-info/licenses/LICENSE
better_py_fp-0.2.0.dist-info/RECORD
