Metadata-Version: 2.4
Name: better-py-fp
Version: 0.2.0
Summary: Functional programming patterns for Python
Project-URL: Homepage, https://github.com/nesalia-inc/better-py
Project-URL: Documentation, https://nesalia-inc.github.io/better-py
Project-URL: Repository, https://github.com/nesalia-inc/better-py
Project-URL: Issues, https://github.com/nesalia-inc/better-py/issues
Project-URL: Changelog, https://github.com/nesalia-inc/better-py/blob/main/CHANGELOG.md
Author-email: nesalia-inc <contact@nesalia.com>
Maintainer-email: nesalia-inc <contact@nesalia.com>
License-Expression: MIT
License-File: AUTHORS.md
License-File: LICENSE
Keywords: collections,either,fp,functional,immutable,maybe,monad,patterns,result,validation
Classifier: Development Status :: 3 - Alpha
Classifier: Intended Audience :: Developers
Classifier: License :: OSI Approved :: MIT License
Classifier: Programming Language :: Python :: 3
Classifier: Programming Language :: Python :: 3.11
Classifier: Programming Language :: Python :: 3.12
Classifier: Programming Language :: Python :: 3.13
Classifier: Topic :: Software Development :: Code Generators
Classifier: Topic :: Software Development :: Libraries :: Python Modules
Classifier: Typing :: Typed
Requires-Python: >=3.11
Provides-Extra: dev
Requires-Dist: hypothesis>=6.0; extra == 'dev'
Requires-Dist: mypy>=1.0; extra == 'dev'
Requires-Dist: pytest-benchmark>=5.0; extra == 'dev'
Requires-Dist: pytest-cov>=5.0; extra == 'dev'
Requires-Dist: pytest-xdist>=3.0; extra == 'dev'
Requires-Dist: pytest>=8.0; extra == 'dev'
